PedGen/__init__.py
PedGen/_version.py
PedGen/core.py
pedgen-0.1.3.dist-info/METADATA
pedgen-0.1.3.dist-info/WHEEL
pedgen-0.1.3.dist-info/licenses/LICENSE
pedgen-0.1.3.dist-info/RECORD
