Metadata-Version: 2.4
Name: PedGen
Version: 0.1.3
Summary: Realistic synthetic pedigree generation, visualization, and file export.
Project-URL: Homepage, https://github.com/taylorngt/pedigree-generator
Project-URL: Issues, https://github.com/taylorngt/pedigree-generator/issues
Author-email: Nick Taylor <taylorngt@cox.net>
License-Expression: MIT
License-File: LICENSE
Classifier: Operating System :: OS Independent
Classifier: Programming Language :: Python :: 3
Requires-Python: >=3.8
Requires-Dist: matplotlib>=3.5.0
Requires-Dist: networkx>=3.0
Requires-Dist: pandas<3.0.0,>=1.3.0
Requires-Dist: pygraphviz>=1.10
